typeset_soren_n-2.0.8.dist-info/METADATA
typeset_soren_n-2.0.8.dist-info/WHEEL
typeset_soren_n-2.0.8.dist-info/licenses/LICENSE
typeset/__init__.py
typeset/__init__.pyi
typeset/py.typed
typeset/typeset.cpython-312-darwin.so
typeset_soren_n-2.0.8.dist-info/RECORD
