Metadata-Version: 2.4
Name: typeset-soren-n
Version: 2.0.8
Classifier: Programming Language :: Rust
Classifier: Programming Language :: Python :: Implementation :: CPython
Classifier: Programming Language :: Python :: Implementation :: PyPy
License-File: LICENSE
License-File: LICENSE
Summary: A DSL for defining source code pretty printers
Keywords: dsl,pretty,printer
Home-Page: https://docs.rs/typeset/latest/typeset/
Author: Soren Norbaek <sorennorbaek@gmail.com>
Author-email: Soren Norbaek <sorennorbaek@gmail.com>
Maintainer-email: Soren Norbaek <sorennorbaek@gmail.com>
Requires-Python: >=3.8
Project-URL: homepage, https://github.com/soren-n/typeset-py
Project-URL: repository, https://github.com/soren-n/typeset-py
Project-URL: documentation, https://github.com/soren-n/typeset-py
